s3pro/__init__.py
s3pro/auth.py
s3pro/clients.py
s3pro/entities.py
s3pro/exceptions.py
s3pro/utils.py
s3pro-0.1.0.dist-info/LICENSE
s3pro-0.1.0.dist-info/METADATA
s3pro-0.1.0.dist-info/WHEEL
s3pro-0.1.0.dist-info/top_level.txt
s3pro-0.1.0.dist-info/RECORD
