Metadata-Version: 2.1
Name: s3pro
Version: 0.1.0
Summary: The best s3 client
Author-email: Alekse Marusich <alekse.marusich@rocshers.com>
License: MIT
Keywords: rocshers,rs3,s3,aws
Classifier: License :: OSI Approved :: MIT License
Classifier: Intended Audience :: Developers
Classifier: Intended Audience :: Information Technology
Classifier: Operating System :: OS Independent
Classifier: Topic :: Software Development :: Libraries :: Python Modules
Classifier: Topic :: Software Development :: Libraries
Classifier: Topic :: Software Development
Classifier: Topic :: System :: Software Distribution
Classifier: Programming Language :: Python :: 3 :: Only
Classifier: Programming Language :: Python :: 3.12
Classifier: Programming Language :: Python :: 3
Classifier: Programming Language :: Python
Requires-Python: >=3.12
License-File: LICENSE
Requires-Dist: httpx >=0.27.2
Provides-Extra: dev
